data/.list-of-algorithms.json
data/__init__.py
data/today.json
sapera/__init__.py
sapera/settings.py
sapera/main/__init__.py
sapera/main/main.py
sapera/scraper/__init__.py
sapera/scraper/updater.cmd
sapera/scraper/updater.py
sapera/scraper/updater.sh
test/__init__.py
sapera-2.1.dist-info/LICENSE
sapera-2.1.dist-info/METADATA
sapera-2.1.dist-info/WHEEL
sapera-2.1.dist-info/entry_points.txt
sapera-2.1.dist-info/top_level.txt
sapera-2.1.dist-info/RECORD
