Metadata-Version: 2.1
Name: sapera
Version: 2.1
Summary: A python package for learning algorithms
Home-page: https://github.com/sarthakchaudhary13/sapera
Author: Sarthak Vineet Kumar
Author-email: sarthakchaudhary13@gmail.com
License: MIT
Project-URL: Bug Reports, https://github.com/sarthakchaudhary13/sapera/issues
Project-URL: Say Thanks!, http://svkumar.me
Project-URL: Source, https://github.com/sarthakchaudhary13/sapera/
Project-URL: Algorithms Source, https://github.com/sarthakchaudhary13/Python
Platform: UNKNOWN
Classifier: Programming Language :: Python :: 3
Classifier: License :: OSI Approved :: MIT License
Classifier: Operating System :: OS Independent
Requires-Python: >=3.6
Requires-Dist: scrapy
